datameta_client/__init__.py
datameta_client/__main__.py
datameta_client/config.py
datameta_client/errors.py
datameta_client/files.py
datameta_client/groups.py
datameta_client/metadatasets.py
datameta_client/printing.py
datameta_client/services.py
datameta_client/shortcuts.py
datameta_client/submissions.py
datameta_client/users.py
datameta_client/utils.py
datameta_client-1.0.1.dist-info/LICENSE
datameta_client-1.0.1.dist-info/METADATA
datameta_client-1.0.1.dist-info/WHEEL
datameta_client-1.0.1.dist-info/entry_points.txt
datameta_client-1.0.1.dist-info/top_level.txt
datameta_client-1.0.1.dist-info/RECORD
