Metadata-Version: 2.1
Name: datameta-client
Version: 1.0.1
Summary: A high-level client for interacting with a DataMeta service
Home-page: https://github.com/ghga-de/datameta-client
Author: Kersten Henrik Breuer
Author-email: k.breuer@dkfz.de
License: Apache 2.0
Download-URL: https://github.com/ghga-de/datameta-client
Platform: UNKNOWN
Classifier: Development Status :: 2 - Pre-Alpha  
Classifier: Intended Audience :: Developers
Classifier: Intended Audience :: Science/Research
Classifier: Intended Audience :: Healthcare Industry 
Classifier: License :: OSI Approved :: Apache Software License
Classifier: Natural Language :: English
Classifier: Operating System :: OS Independent
Classifier: Operating System :: POSIX
Classifier: Operating System :: POSIX :: Linux
Classifier: Operating System :: MacOS :: MacOS X
Classifier: Operating System :: Microsoft :: Windows
Classifier: Programming Language :: Python :: 3
Classifier: Topic :: Scientific/Engineering
Classifier: Topic :: Scientific/Engineering :: Bio-Informatics
Classifier: Topic :: Scientific/Engineering :: Information Analysis
Classifier: Topic :: Scientific/Engineering :: Medical Science Apps.
License-File: LICENSE
Requires-Dist: typer
Requires-Dist: datameta-client-lib (<2,>=1.4.0)
Requires-Dist: pyyaml
Requires-Dist: requests
Provides-Extra: testing
Requires-Dist: pytest ; extra == 'testing'
Requires-Dist: pytest-cov ; extra == 'testing'
